README.md
setup.cfg
setup.py
TOPSIS_Aditi_101803650/__init__.py
TOPSIS_Aditi_101803650/topsis.py
TOPSIS_Aditi_101803650.egg-info/PKG-INFO
TOPSIS_Aditi_101803650.egg-info/SOURCES.txt
TOPSIS_Aditi_101803650.egg-info/dependency_links.txt
TOPSIS_Aditi_101803650.egg-info/requires.txt
TOPSIS_Aditi_101803650.egg-info/top_level.txt