Metadata-Version: 2.1
Name: TOPSIS-Aditi-101803650
Version: 0.2
Summary: Pyhon Package for TOPSIS score
Home-page: https://github.com/Aditibansal2603/TOPSIS_Aditi_101803650
Author: Aditi Bansal
Author-email: abansal2_be18@thapar.edu
License: MIT
Download-URL: https://github.com/Aditibansal2603/TOPSIS_Aditi_101803650/archive/v_01.tar.gz
Platform: UNKNOWN
Classifier: Development Status :: 3 - Alpha
Classifier: Intended Audience :: Developers
Classifier: License :: OSI Approved :: MIT License
Classifier: Programming Language :: Python :: 3.4
Classifier: Programming Language :: Python :: 3.5
Classifier: Programming Language :: Python :: 3.6
Classifier: Programming Language :: Python :: 3.7
Classifier: Programming Language :: Python :: 3.8
